{
  "datasource": {
    "type": "prometheus",
    "uid": "prometheus"
  },
  "fieldConfig": {
    "defaults": {
      "color": {
        "mode": "palette-classic"
      },
      "custom": {
        "axisBorderShow": false,
        "axisCenteredZero": false,
        "axisColorMode": "text",
        "axisLabel": "",
        "axisPlacement": "auto",
        "barAlignment": 0,
        "drawStyle": "line",
        "fillOpacity": 10,
        "gradientMode": "none",
        "hideFrom": {
          "legend": false,
          "tooltip": false,
          "viz": false
        },
        "insertNulls": false,
        "lineInterpolation": "linear",
        "lineWidth": 1,
        "pointSize": 5,
        "scaleDistribution": {
          "type": "linear"
        },
        "showPoints": "never",
        "spanNulls": false,
        "stacking": {
          "group": "A",
          "mode": "none"
        },
        "thresholdsStyle": {
          "mode": "off"
        }
      },
      "mappings": [],
      "thresholds": {
        "mode": "absolute",
        "steps": [
          {
            "color": "green",
            "value": 0
          }
        ]
      },
      "unit": "short"
    },
    "overrides": []
  },
  "options": {
    "legend": {
      "calcs": [
        "lastNotNull"
      ],
      "displayMode": "table",
      "placement": "bottom",
      "showLegend": true
    },
    "tooltip": {
      "hideZeros": false,
      "mode": "multi",
      "sort": "desc"
    }
  },
  "targets": [
    {
      "datasource": {
        "type": "prometheus",
        "uid": "prometheus"
      },
      "editorMode": "code",
      "expr": "rate(aprs_envelope_channel_blocked_total{environment=~\"$environment\"}[1m]) * 60",
      "legendFormat": "Blocked Sends/min",
      "range": true,
      "refId": "A"
    }
  ],
  "title": "Envelope Channel Blocked Sends",
  "type": "timeseries"
}
